checkdigit/__init__.py
checkdigit/_data.py
checkdigit/crc.py
checkdigit/gs1.py
checkdigit/isbn.py
checkdigit/luhn.py
checkdigit/parity.py
checkdigit/py.typed
checkdigit/verhoeff.py
checkdigit-0.5.0.dist-info/LICENSE
checkdigit-0.5.0.dist-info/METADATA
checkdigit-0.5.0.dist-info/WHEEL
checkdigit-0.5.0.dist-info/RECORD
