Metadata-Version: 2.1
Name: checkdigit
Version: 0.5.0
Summary: A check digit library for data validation
Home-page: https://checkdigit.rtfd.io
License: GPL-3.0-or-later
Keywords: Check Digits,Validation,ISBN,GS1,Luhn
Author: harens
Author-email: harensdeveloper@gmail.com
Maintainer: harens
Maintainer-email: harensdeveloper@gmail.com
Requires-Python: >=3.7,<4.0
Classifier: Intended Audience :: Developers
Classifier: License :: OSI Approved :: GNU General Public License v3 or later (GPLv3+)
Classifier: Natural Language :: English
Classifier: Operating System :: OS Independent
Classifier: Programming Language :: Python :: 3
Classifier: Programming Language :: Python :: 3.7
Classifier: Programming Language :: Python :: 3.8
Classifier: Programming Language :: Python :: 3.9
Classifier: Programming Language :: Python :: 3.10
Classifier: Programming Language :: Python :: 3.11
Classifier: Typing :: Typed
Project-URL: Bug Tracker, https://github.com/harens/checkdigit/issues
Project-URL: Documentation, https://checkdigit.rtfd.io
Project-URL: Repository, https://github.com/harens/checkdigit
